nl2query/__init__.py
nl2query/base.py
nl2query/cypherquery.py
nl2query/kustoquery.py
nl2query/mongoquery.py
nl2query/pandasquery.py
nl2query-0.1.8.dist-info/LICENSE
nl2query-0.1.8.dist-info/METADATA
nl2query-0.1.8.dist-info/WHEEL
nl2query-0.1.8.dist-info/RECORD
