Metadata-Version: 2.1
Name: nl2query
Version: 0.1.8
Summary: 
Author: Chirayu-Tripathi
Author-email: chirayutripathi7@gmail.com
Requires-Python: >=3.8,<4.0
Classifier: Programming Language :: Python :: 3
Classifier: Programming Language :: Python :: 3.8
Classifier: Programming Language :: Python :: 3.9
Classifier: Programming Language :: Python :: 3.10
Classifier: Programming Language :: Python :: 3.11
Classifier: Programming Language :: Python :: 3.12
Requires-Dist: accelerate (>=0.29.3,<0.30.0)
Requires-Dist: bitsandbytes (>=0.43.1,<0.44.0)
Requires-Dist: einops (>=0.7.0,<0.8.0)
Requires-Dist: pandas (>=1.5.3,<2.0.0)
Requires-Dist: peft (>=0.5.0,<0.6.0)
Requires-Dist: regex (>=2023.6.3,<2024.0.0)
Requires-Dist: torch (>=2.0.1,<3.0.0)
Requires-Dist: transformers (>=4.39.0,<5.0.0)
